{
  "rank_titles": {
    "level_60": "Piston Punisher",
    "level_20": "Betting On Red and Black",
    "level_70": "72-Game Winner",
    "level_100": "Champion of Chicago Bulls",
    "level_5": "Benny the Bull's Buddy",
    "level_15": "Madhouse Member",
    "level_40": "Slick as Sloan",
    "level_80": "Eastern Conference Champ",
    "level_30": "Action Paxson",
    "level_50": "Straight Pippen'",
    "level_10": "Bull Backer",
    "level_90": "Like Mike",
    "level_25": "That's No Bull"
  },
  "play_count": 872430,
  "description": "Mess with the Bulls, get the horns."
}