{
  "rank_titles": {
    "level_60": "Bishop's Wife",
    "level_20": "Scrooged",
    "level_70": "Mogwai Offspring",
    "level_100": "Champion of Christmas Movies",
    "level_5": "On a Christmas Vacation",
    "level_15": "In Love, Actually",
    "level_40": "Red-Nosed Reindeer",
    "level_80": "Captive in the Nakatomi Plaza",
    "level_30": "Elf in the City",
    "level_50": "34th Street Miracle",
    "level_10": "Bad Santa",
    "level_90": "Santa on Trial",
    "level_25": "Mayor of Christmastown"
  },
  "play_count": 4465724,
  "description": "Merry Christmas, you filthy animal."
}