{
  "rank_titles": {
    "level_60": "Sweet Sixteen Bound",
    "level_20": "Final Four MOP",
    "level_70": "Elite Eight Sweetheart",
    "level_100": "Champion of College Basketball",
    "level_5": "Breaking .500",
    "level_15": "NIT Invitee",
    "level_40": "A Bad Seed",
    "level_80": "Final Four Fighter",
    "level_30": "Play-In Team",
    "level_50": "Mid-Major Upset",
    "level_10": "Polishing the Resume",
    "level_90": "All-Tourney Team",
    "level_25": "Just Happy to Be Here"
  },
  "play_count": 956491,
  "description": "March Madness. It's truly insane."
}