{
  "rank_titles": {
    "level_60": "Live-Aid Concert Roadie",
    "level_20": "Commodore 64 Hacker",
    "level_70": "Watched the First Wrestlemania",
    "level_100": "Champion of 80s History",
    "level_5": "Pac-Man",
    "level_15": "Raised on The Brat Pack",
    "level_40": "The First Liposuction Patient",
    "level_80": "Broke Stockbroker",
    "level_30": "Found the Titanic",
    "level_50": "Discovered a Hole in the Ozone Layer",
    "level_10": "Addicted to New Coke",
    "level_90": "Born in the 80s",
    "level_25": "Passed by Halley's Comet"
  },
  "play_count": 353229,
  "description": "Where everybody knows your name."
}