{
  "rank_titles": {
    "level_60": "Questioning Everything",
    "level_20": "Reckless Riddler",
    "level_70": "Irritating Interrogator",
    "level_100": "Champion of What is the Question?",
    "level_5": "Cool Questioner",
    "level_15": "Asking a Silly Question",
    "level_40": "Seeking Explanations",
    "level_80": "The One With the Answer",
    "level_30": "Working on Results",
    "level_50": "Inspiring Inquistor",
    "level_10": "Imaginative Investigator",
    "level_90": "Quirky Questor",
    "level_25": "Qualified Querier"
  },
  "play_count": 41878,
  "description": "Don't be afraid to ask questions."
}