{
  "rank_titles": {
    "level_60": "Dealing Like Drysdale",
    "level_20": "Superbas Effort",
    "level_70": "The Duke",
    "level_100": "Champion of LA Dodgers",
    "level_5": "New To The Blue Crew",
    "level_15": "Honorary Bum",
    "level_40": "Cool as Campy",
    "level_80": "Pure Vin-sanity",
    "level_30": "Chavez Ravine Rowdy",
    "level_50": "Kaufax Kin",
    "level_10": "Dodger Dog",
    "level_90": "Lord of L.A.",
    "level_25": "Gritty as Gibson"
  },
  "play_count": 233872,
  "description": "The Boys in Blue - From Brooklyn to LA."
}