{
  "rank_titles": {
    "level_60": "Beta Romeo",
    "level_20": "Betacritic",
    "level_70": "Beta Safe than Sorry",
    "level_100": "Champion of QuizUp Beta",
    "level_5": "Beta Tester",
    "level_15": "Beta Half",
    "level_40": "Beta Male",
    "level_80": "Beta Dog",
    "level_30": "Beta Fish",
    "level_50": "Beta Vulgaris",
    "level_10": "Beta Blocker",
    "level_90": "Beta off Alone",
    "level_25": "Beta than Nothing"
  },
  "play_count": 232288,
  "description": "All about QuizUp in one quiz...up?"
}