{
  "rank_titles": {
    "level_60": "Pirate of Penzance",
    "level_20": "Cat on a Hot Tin Roof",
    "level_70": "My Fair Lady",
    "level_100": "Champion of Theatre",
    "level_5": "Playboy of the Western World",
    "level_15": "Afraid of Virginia Woolf",
    "level_40": "Doctor Faustus",
    "level_80": "Fiddler on the Roof",
    "level_30": "Bullet Over Broadway",
    "level_50": "Lady Windemere's Fan",
    "level_10": "The Wiz",
    "level_90": "The Producer",
    "level_25": "A Streetcar Names Desire"
  },
  "play_count": 1038359,
  "description": "Break a leg!"
}